{
  "generated": "2026-04-09",
  "description": "Programmes d'affiliation Baymora — recherche complète. Priorité 1 = inscription immédiate (programmes ouverts). Priorité 2 = contact direct cette semaine.",
  "partenaires": [
    {
      "id": "booking",
      "nom": "Booking.com",
      "categorie": "Hébergement",
      "priorite": "PRIORITÉ 1",
      "statut": "Ouvert",
      "url_inscription": "https://www.booking.com/affiliate-program/v2/index.html",
      "url_alternative": "https://www.cj.com/en-gb/publisher/partners/booking.com",
      "plateforme": "Direct (Booking Affiliate Partner) ou CJ Affiliate",
      "commission": "25–40% de la commission Booking (soit ~4% du montant total de la réservation hôtel, 6% location voiture, 2€/vol)",
      "cookie_duration": "30 jours",
      "conditions": "Inscription gratuite, approbation sous 48h. Pas de minimum de trafic déclaré. Intégration via widget, lien texte ou API.",
      "notes": "Programme le plus accessible. Idéal pour démarrer immédiatement. Taux réel : ~4% sur hébergement."
    },
    {
      "id": "trainline",
      "nom": "Trainline",
      "categorie": "Transport ferroviaire",
      "priorite": "PRIORITÉ 1",
      "statut": "Ouvert via Partnerize",
      "url_inscription": "https://www.thetrainline.com/about-us/partnerships/affiliates",
      "url_alternative": "https://www.travelpayouts.com/en/offers/trainline-affiliate-program",
      "plateforme": "Partnerize (anciennement Awin pour certains marchés)",
      "commission": "Jusqu'à 20% CPA sur ventes de billets train et bus. Flat rate : ~1,50–3€ par réservation.",
      "cookie_duration": "30 jours",
      "conditions": "Inscription via Partnerize. Approbation nécessaire. Option non-lucratif disponible.",
      "notes": "Excellent pour les parcours Maya avec étapes train. Couvre UK, France, Europe."
    },
    {
      "id": "getyourguide",
      "nom": "GetYourGuide",
      "categorie": "Activités & Expériences",
      "priorite": "PRIORITÉ 1",
      "statut": "Ouvert",
      "url_inscription": "https://partner.getyourguide.com/",
      "plateforme": "Direct (GetYourGuide Partner Program)",
      "commission": "8% minimum sur chaque réservation. Négociable à la hausse selon volume.",
      "cookie_duration": "30 jours",
      "conditions": "Inscription gratuite. Paiement mensuel. Suite analytics intégrée. Pas de minimum de trafic.",
      "notes": "Idéal pour les tags :::PLACES::: type activités. Commission compétitive sur expériences premium."
    },
    {
      "id": "viator",
      "nom": "Viator (TripAdvisor)",
      "categorie": "Activités & Expériences",
      "priorite": "PRIORITÉ 1",
      "statut": "Ouvert",
      "url_inscription": "https://partnerresources.viator.com/",
      "plateforme": "Direct (Viator Partner Resources)",
      "commission": "8% sur chaque expérience réservée dans les 30 jours suivant le clic.",
      "cookie_duration": "30 jours",
      "conditions": "Inscription gratuite. Catalogue de 300 000+ expériences dans le monde.",
      "notes": "Concurrent direct de GetYourGuide. Couvre mieux les destinations US et Asie."
    },
    {
      "id": "skyscanner",
      "nom": "Skyscanner",
      "categorie": "Vols",
      "priorite": "PRIORITÉ 1",
      "statut": "Ouvert",
      "url_inscription": "https://www.partners.skyscanner.net/product/affiliates",
      "plateforme": "Direct (Skyscanner Partners)",
      "commission": "20% des revenus Skyscanner sur chaque vol réservé (soit ~50% de leur commission). Pas de montant fixe.",
      "cookie_duration": "30 jours",
      "conditions": "Inscription gratuite. Widgets, bannières et liens texte disponibles.",
      "notes": "Commission en % des revenus Skyscanner, pas du prix du billet. Utile pour les tags :::JOURNEY::: vols."
    },
    {
      "id": "kiwi",
      "nom": "Kiwi.com",
      "categorie": "Vols",
      "priorite": "PRIORITÉ 1",
      "statut": "Ouvert",
      "url_inscription": "https://www.kiwi.com/content/affiliates",
      "url_alternative": "https://www.travelpayouts.com/en/offers/kiwi-affiliate-program",
      "plateforme": "Travelpayouts ou direct",
      "commission": "3% du prix total du billet. Panier moyen ~450€ → ~13,50€/réservation.",
      "cookie_duration": "30 jours",
      "conditions": "Inscription gratuite. Spécialisé vols avec correspondances complexes (Nomad tickets).",
      "notes": "Complément de Skyscanner pour les vols multi-escales. Commission plus faible mais catalogue unique."
    },
    {
      "id": "rentalcars",
      "nom": "Rentalcars.com",
      "categorie": "Location de voiture",
      "priorite": "PRIORITÉ 1",
      "statut": "Ouvert",
      "url_inscription": "https://partnerships.booking.com/rentalcarsconnect",
      "url_alternative": "https://www.cj.com/advertiser/rentalcars",
      "plateforme": "CJ Affiliate ou Booking.com RentalCars Connect",
      "commission": "6% sur chaque location confirmée.",
      "cookie_duration": "30 jours",
      "conditions": "Inscription via CJ Affiliate. Pas de minimum de trafic. Couverture mondiale.",
      "notes": "Appartient au groupe Booking Holdings. Intégration simple via CJ."
    },
    {
      "id": "chapka",
      "nom": "Chapka Assurances",
      "categorie": "Assurance voyage",
      "priorite": "PRIORITÉ 1",
      "statut": "Ouvert (via GoByAVA/Awin)",
      "url_inscription": "https://www.chapkadirect.fr/index.php?action=partenaires",
      "plateforme": "Awin (via GoByAVA) ou direct",
      "commission": "5–10% de la prime d'assurance. Remise de -5% offerte aux clients via code affilié.",
      "cookie_duration": "30 jours",
      "conditions": "Inscription via page partenaires Chapka ou Awin. Marque française reconnue.",
      "notes": "Valeur ajoutée pour les parcours Maya incluant assurance voyage. Spécialiste PVT et séjours longue durée."
    },
    {
      "id": "gettransfer",
      "nom": "GetTransfer",
      "categorie": "Transferts & Chauffeurs",
      "priorite": "PRIORITÉ 1",
      "statut": "Ouvert",
      "url_inscription": "https://gettransfer.com/en/agent/new",
      "url_alternative": "https://www.travelpayouts.com/en/offers/gettransfer-affiliate-program",
      "plateforme": "Direct (programme agents) ou Travelpayouts",
      "commission": "4–25% selon le type de transfert. Jusqu'à 70% des revenus GetTransfer pour les agents actifs. Moyenne : ~18€/réservation.",
      "cookie_duration": "30 jours",
      "conditions": "Inscription gratuite. 150+ pays. Programme agents très généreux pour volume élevé.",
      "notes": "Idéal pour les tags :::JOURNEY::: transferts aéroport et chauffeurs privés."
    },
    {
      "id": "airalo",
      "nom": "Airalo eSIM",
      "categorie": "Connectivité voyage",
      "priorite": "PRIORITÉ 1",
      "statut": "Ouvert",
      "url_inscription": "https://partners.airalo.com/solutions/affiliates",
      "plateforme": "Direct (Airalo Partners)",
      "commission": "10% par vente d'eSIM. Codes promo disponibles.",
      "cookie_duration": "30 jours",
      "conditions": "Inscription gratuite. Leader mondial eSIM voyage. Couverture 200+ pays.",
      "notes": "Produit complémentaire naturel pour les voyageurs internationaux. Facile à intégrer dans les recommandations Maya."
    },
    {
      "id": "staycation",
      "nom": "Staycation",
      "categorie": "Hébergement week-end",
      "priorite": "PRIORITÉ 2",
      "statut": "Contact direct",
      "url_inscription": null,
      "contact": "contact@staycation.co",
      "plateforme": "Direct",
      "commission": "À négocier (estimé 5–10% sur réservation)",
      "cookie_duration": "À vérifier",
      "conditions": "Partenariat direct. Spécialiste staycations et week-ends de luxe en France.",
      "notes": "Très aligné avec la proposition Baymora. Contacter pour partenariat exclusif ou co-branding."
    },
    {
      "id": "lecollectionist",
      "nom": "Le Collectionist",
      "categorie": "Locations de luxe",
      "priorite": "PRIORITÉ 2",
      "statut": "Contact direct (agences partenaires)",
      "url_inscription": "https://www.lecollectionist.com/fr/agences-partenaires",
      "contact": "partenaires@lecollectionist.com",
      "plateforme": "Direct",
      "commission": "À négocier (programme agences partenaires)",
      "cookie_duration": "À vérifier",
      "conditions": "Programme dédié aux agences de voyage premium. Villas et maisons d'exception.",
      "notes": "Parfait pour les offres haut de gamme Baymora. Formulaire agences disponible sur leur site."
    },
    {
      "id": "mrandmrssmith",
      "nom": "Mr & Mrs Smith",
      "categorie": "Hôtels boutique de luxe",
      "priorite": "PRIORITÉ 2",
      "statut": "Sur candidature (Rakuten)",
      "url_inscription": "https://affiliateprograms.com/p/mr-mrs-smith/",
      "contact": "affiliates@mrandmrssmith.com",
      "plateforme": "Rakuten Advertising",
      "commission": "6% sur réservation hôtel. Cookie 30 jours.",
      "cookie_duration": "30 jours",
      "conditions": "Programme via Rakuten. Candidature requise. Hôtels boutique sélectionnés dans le monde entier.",
      "notes": "Très cohérent avec le positionnement Baymora. Commission correcte sur hôtels premium."
    },
    {
      "id": "privatefly",
      "nom": "PrivateFly",
      "categorie": "Aviation privée",
      "priorite": "PRIORITÉ 2",
      "statut": "Contact direct",
      "url_inscription": null,
      "contact": "partnerships@privatefly.com",
      "plateforme": "Direct",
      "commission": "À négocier (estimé 2–5% sur charter)",
      "cookie_duration": "À vérifier",
      "conditions": "Partenariat direct. Spécialiste jets privés. Appartient au groupe Air Charter Service.",
      "notes": "Pour les clients VIP Baymora. Commission en valeur absolue élevée vu les montants des charters."
    },
    {
      "id": "blacklane",
      "nom": "Blacklane",
      "categorie": "Chauffeurs premium",
      "priorite": "PRIORITÉ 2",
      "statut": "Contact direct",
      "url_inscription": "https://www.blacklane.com/en/partners/",
      "contact": "partners@blacklane.com",
      "plateforme": "Direct",
      "commission": "10% flat sur chaque réservation (confirmé par leur documentation chauffeurs/agents).",
      "cookie_duration": "À vérifier",
      "conditions": "Programme partenaires dédié. Paiement par virement bancaire. Présence dans 50+ pays.",
      "notes": "Idéal pour les transferts premium dans les tags :::JOURNEY:::. Commission confirmée à 10%."
    },
    {
      "id": "clickandboat",
      "nom": "Click&Boat",
      "categorie": "Yachts & Nautisme",
      "priorite": "PRIORITÉ 1",
      "statut": "Ouvert",
      "url_inscription": "https://www.clickandboat.com/partenaires",
      "commission": "5-8%",
      "cookie_duration": "30 jours",
      "conditions": "Inscription gratuite, approbation rapide.",
      "notes": "Leader location de bateaux en Europe."
    },
    {
      "id": "samboat",
      "nom": "SamBoat",
      "categorie": "Yachts & Nautisme",
      "priorite": "PRIORITÉ 1",
      "statut": "Ouvert",
      "url_inscription": "https://www.samboat.fr/affiliation",
      "commission": "5-8%",
      "cookie_duration": "30 jours",
      "conditions": "Inscription gratuite.",
      "notes": "Concurrent direct Click&Boat, forte présence Méditerranée."
    },
    {
      "id": "flyvictor",
      "nom": "Victor",
      "categorie": "Aviation Privée",
      "priorite": "PRIORITÉ 1",
      "statut": "Ouvert",
      "url_inscription": "https://www.flyvictor.com/en/partners",
      "commission": "2-5%",
      "cookie_duration": "30 jours",
      "conditions": "Partenariat B2B, approbation requise.",
      "notes": "Jets privés premium, clientèle UHNW."
    },
    {
      "id": "jettly",
      "nom": "Jettly",
      "categorie": "Aviation Privée",
      "priorite": "PRIORITÉ 2",
      "statut": "Ouvert",
      "url_inscription": "https://www.jettly.com/affiliates",
      "commission": "3-5%",
      "cookie_duration": "30 jours",
      "conditions": "Inscription gratuite.",
      "notes": "Marketplace jets privés, bons tarifs last-minute."
    },
    {
      "id": "europcar_prestige",
      "nom": "Europcar Prestige",
      "categorie": "Location Voiture Luxe",
      "priorite": "PRIORITÉ 1",
      "statut": "Ouvert",
      "url_inscription": "https://www.europcar.com/en-gb/affiliate-program",
      "commission": "5-8%",
      "cookie_duration": "30 jours",
      "conditions": "Via Awin ou direct.",
      "notes": "Gamme prestige : Ferrari, Lamborghini, Bentley."
    },
    {
      "id": "hertz_dream",
      "nom": "Hertz Dream Collection",
      "categorie": "Location Voiture Luxe",
      "priorite": "PRIORITÉ 1",
      "statut": "Ouvert",
      "url_inscription": "https://www.hertz.com/rentacar/affiliate",
      "commission": "5-8%",
      "cookie_duration": "30 jours",
      "conditions": "Via CJ Affiliate.",
      "notes": "Collection prestige disponible dans les grandes villes."
    },
    {
      "id": "turo",
      "nom": "Turo",
      "categorie": "Location Voiture Luxe",
      "priorite": "PRIORITÉ 2",
      "statut": "Ouvert",
      "url_inscription": "https://turo.com/en-us/affiliates",
      "commission": "3-5%",
      "cookie_duration": "30 jours",
      "conditions": "Via Impact.",
      "notes": "Peer-to-peer, accès aux voitures rares et de collection."
    },
    {
      "id": "wheely",
      "nom": "Wheely",
      "categorie": "Chauffeurs Premium",
      "priorite": "PRIORITÉ 1",
      "statut": "Ouvert",
      "url_inscription": "https://wheely.com/en/business",
      "commission": "8-10%",
      "cookie_duration": "30 jours",
      "conditions": "Partenariat B2B.",
      "notes": "VTC ultra-premium, chauffeurs en costume, app élégante."
    },
    {
      "id": "tablethotels",
      "nom": "Tablet Hotels",
      "categorie": "Hôtels de Luxe",
      "priorite": "PRIORITÉ 1",
      "statut": "Ouvert",
      "url_inscription": "https://www.tablethotels.com/en/affiliate-program",
      "commission": "5-8%",
      "cookie_duration": "30 jours",
      "conditions": "Inscription gratuite.",
      "notes": "Sélection curatée des meilleurs hôtels design et boutique."
    },
    {
      "id": "slh",
      "nom": "Small Luxury Hotels",
      "categorie": "Hôtels de Luxe",
      "priorite": "PRIORITÉ 1",
      "statut": "Ouvert",
      "url_inscription": "https://www.slh.com/affiliates",
      "commission": "5%",
      "cookie_duration": "30 jours",
      "conditions": "Via Awin.",
      "notes": "Collection d'hôtels boutique de luxe dans 90 pays."
    },
    {
      "id": "designhotels",
      "nom": "Design Hotels",
      "categorie": "Hôtels de Luxe",
      "priorite": "PRIORITÉ 1",
      "statut": "Ouvert",
      "url_inscription": "https://www.designhotels.com/affiliate",
      "commission": "4-6%",
      "cookie_duration": "30 jours",
      "conditions": "Inscription gratuite.",
      "notes": "Hôtels architecturaux et design, clientèle créative premium."
    },
    {
      "id": "villanovo",
      "nom": "Villanovo",
      "categorie": "Villas & Maisons de Luxe",
      "priorite": "PRIORITÉ 1",
      "statut": "Ouvert",
      "url_inscription": "https://www.villanovo.fr/affiliation",
      "commission": "3-5%",
      "cookie_duration": "30 jours",
      "conditions": "Inscription gratuite.",
      "notes": "Villas de luxe en France et Méditerranée, curatées."
    },
    {
      "id": "onefinestay",
      "nom": "Onefinestay",
      "categorie": "Villas & Maisons de Luxe",
      "priorite": "PRIORITÉ 2",
      "statut": "Ouvert",
      "url_inscription": "https://www.onefinestay.com/partners",
      "commission": "4-6%",
      "cookie_duration": "30 jours",
      "conditions": "Partenariat B2B.",
      "notes": "Maisons et appartements de luxe dans les grandes villes."
    },
    {
      "id": "plumguide",
      "nom": "Plum Guide",
      "categorie": "Villas & Maisons de Luxe",
      "priorite": "PRIORITÉ 2",
      "statut": "Ouvert",
      "url_inscription": "https://www.plumguide.com/affiliates",
      "commission": "3-5%",
      "cookie_duration": "30 jours",
      "conditions": "Via Impact.",
      "notes": "Sélection ultra-curatée (top 3% des propriétés testées)."
    },
    {
      "id": "farfetch",
      "nom": "Farfetch",
      "categorie": "Shopping Luxe",
      "priorite": "PRIORITÉ 1",
      "statut": "Ouvert",
      "url_inscription": "https://www.farfetch.com/affiliates",
      "commission": "5-8%",
      "cookie_duration": "30 jours",
      "conditions": "Via Awin ou Rakuten.",
      "notes": "Marketplace mode luxe, 700+ boutiques mondiales."
    },
    {
      "id": "netaporter",
      "nom": "Net-a-Porter",
      "categorie": "Shopping Luxe",
      "priorite": "PRIORITÉ 1",
      "statut": "Ouvert",
      "url_inscription": "https://www.net-a-porter.com/en-gb/affiliates",
      "commission": "5-7%",
      "cookie_duration": "30 jours",
      "conditions": "Via Rakuten.",
      "notes": "Mode luxe femme, éditorial premium, clientèle fidèle."
    },
    {
      "id": "24s",
      "nom": "24S",
      "categorie": "Shopping Luxe",
      "priorite": "PRIORITÉ 1",
      "statut": "Ouvert",
      "url_inscription": "https://www.24s.com/en-fr/affiliate-program",
      "commission": "5-8%",
      "cookie_duration": "30 jours",
      "conditions": "Via Awin.",
      "notes": "Filiale LVMH, accès aux grandes maisons françaises."
    },
    {
      "id": "mytheresa",
      "nom": "Mytheresa",
      "categorie": "Shopping Luxe",
      "priorite": "PRIORITÉ 2",
      "statut": "Ouvert",
      "url_inscription": "https://www.mytheresa.com/en-de/affiliate-program.html",
      "commission": "5-8%",
      "cookie_duration": "30 jours",
      "conditions": "Via Awin.",
      "notes": "Mode luxe ultra-premium, clientèle internationale."
    },
    {
      "id": "interflora",
      "nom": "Interflora",
      "categorie": "Cadeaux & Fleurs",
      "priorite": "PRIORITÉ 1",
      "statut": "Ouvert",
      "url_inscription": "https://www.interflora.fr/affiliation",
      "commission": "10-15%",
      "cookie_duration": "30 jours",
      "conditions": "Via Awin.",
      "notes": "Livraison fleurs internationale, idéal pour occasions spéciales."
    },
    {
      "id": "bloomandwild",
      "nom": "Bloom & Wild",
      "categorie": "Cadeaux & Fleurs",
      "priorite": "PRIORITÉ 1",
      "statut": "Ouvert",
      "url_inscription": "https://www.bloomandwild.com/affiliates",
      "commission": "10-15%",
      "cookie_duration": "30 jours",
      "conditions": "Via Awin.",
      "notes": "Bouquets premium livrés en boîte aux lettres, très tendance."
    },
    {
      "id": "smartbox",
      "nom": "Smartbox",
      "categorie": "Cadeaux & Coffrets",
      "priorite": "PRIORITÉ 1",
      "statut": "Ouvert",
      "url_inscription": "https://www.smartbox.com/fr/affiliation",
      "commission": "8-12%",
      "cookie_duration": "30 jours",
      "conditions": "Via Awin.",
      "notes": "Coffrets cadeaux expériences, très fort en France."
    },
    {
      "id": "fever",
      "nom": "Fever",
      "categorie": "Événements & Sorties",
      "priorite": "PRIORITÉ 1",
      "statut": "Ouvert",
      "url_inscription": "https://feverup.com/en/affiliates",
      "commission": "5-10%",
      "cookie_duration": "30 jours",
      "conditions": "Via Impact.",
      "notes": "Événements exclusifs, expositions immersives, soirées."
    },
    {
      "id": "headout",
      "nom": "Headout",
      "categorie": "Événements & Sorties",
      "priorite": "PRIORITÉ 1",
      "statut": "Ouvert",
      "url_inscription": "https://www.headout.com/affiliates",
      "commission": "8-10%",
      "cookie_duration": "30 jours",
      "conditions": "Via Impact.",
      "notes": "Activités et expériences dans les grandes villes mondiales."
    },
    {
      "id": "treatwell",
      "nom": "Treatwell",
      "categorie": "Bien-être & Beauté",
      "priorite": "PRIORITÉ 1",
      "statut": "Ouvert",
      "url_inscription": "https://www.treatwell.fr/affiliation",
      "commission": "8-12%",
      "cookie_duration": "30 jours",
      "conditions": "Via Awin.",
      "notes": "Réservation spa, coiffeur, beauté en ligne."
    },
    {
      "id": "opentable",
      "nom": "OpenTable",
      "categorie": "Restaurants",
      "priorite": "PRIORITÉ 1",
      "statut": "Ouvert",
      "url_inscription": "https://www.opentable.com/partners/affiliates",
      "commission": "1-2$/résa",
      "cookie_duration": "30 jours",
      "conditions": "Via CJ Affiliate.",
      "notes": "Réservations restaurants internationaux, fort aux USA/UK."
    },
    {
      "id": "holafly",
      "nom": "Holafly",
      "categorie": "eSIM & Connectivité",
      "priorite": "PRIORITÉ 1",
      "statut": "Ouvert",
      "url_inscription": "https://www.holafly.com/affiliates",
      "commission": "12%",
      "cookie_duration": "30 jours",
      "conditions": "Inscription gratuite.",
      "notes": "eSIM internationale, idéal pour voyageurs fréquents."
    },
    {
      "id": "wise",
      "nom": "Wise",
      "categorie": "Finance & Change",
      "priorite": "PRIORITÉ 1",
      "statut": "Ouvert",
      "url_inscription": "https://wise.com/partners/affiliates",
      "commission": "25-50€/signup",
      "cookie_duration": "30 jours",
      "conditions": "Via Impact.",
      "notes": "Transferts internationaux sans frais cachés, carte multi-devises."
    },
    {
      "id": "safetywing",
      "nom": "SafetyWing",
      "categorie": "Assurance Voyage",
      "priorite": "PRIORITÉ 1",
      "statut": "Ouvert",
      "url_inscription": "https://safetywing.com/nomad-insurance/affiliate",
      "commission": "10%",
      "cookie_duration": "30 jours",
      "conditions": "Inscription gratuite.",
      "notes": "Assurance voyage nomade, très flexible, idéal long séjour."
    },
    {
      "id": "worldnomads",
      "nom": "World Nomads",
      "categorie": "Assurance Voyage",
      "priorite": "PRIORITÉ 1",
      "statut": "Ouvert",
      "url_inscription": "https://www.worldnomads.com/affiliates",
      "commission": "10%",
      "cookie_duration": "30 jours",
      "conditions": "Via Commission Junction.",
      "notes": "Assurance aventure et sport extrême, recommandée par Lonely Planet."
    },
    {
      "id": "golfbookings",
      "nom": "Golf Bookings",
      "categorie": "Sport & Golf",
      "priorite": "PRIORITÉ 2",
      "statut": "Ouvert",
      "url_inscription": "https://www.golfbookings.com/affiliates",
      "commission": "5%",
      "cookie_duration": "30 jours",
      "conditions": "Inscription gratuite.",
      "notes": "Réservation green fees dans les meilleurs golfs mondiaux."
    }
  ],
  "resume": {
    "priorite_1_immediat": [
      "Booking.com → booking.com/affiliate-program/v2/index.html",
      "Trainline → thetrainline.com/about-us/partnerships/affiliates",
      "GetYourGuide → partner.getyourguide.com",
      "Viator → partnerresources.viator.com",
      "Skyscanner → partners.skyscanner.net/product/affiliates",
      "Kiwi.com → kiwi.com/content/affiliates",
      "Rentalcars.com → partnerships.booking.com/rentalcarsconnect",
      "Chapka → chapkadirect.fr/index.php?action=partenaires",
      "GetTransfer → gettransfer.com/en/agent/new",
      "Airalo → partners.airalo.com/solutions/affiliates"
    ],
    "priorite_2_contact": [
      "Staycation → contact@staycation.co",
      "Le Collectionist → partenaires@lecollectionist.com",
      "Mr & Mrs Smith → affiliates@mrandmrssmith.com",
      "PrivateFly → partnerships@privatefly.com",
      "Blacklane → partners@blacklane.com"
    ],
    "total_partenaires": 45
  }
}